CONTRIBUTING.rst
LICENSE.txt
MANIFEST.in
README.rst
example-era5.py
example-glaciers.py
setup.cfg
setup.py
tox.ini
cdsapi/__init__.py
cdsapi/api.py
cdsapitaka.egg-info/PKG-INFO
cdsapitaka.egg-info/SOURCES.txt
cdsapitaka.egg-info/dependency_links.txt
cdsapitaka.egg-info/requires.txt
cdsapitaka.egg-info/top_level.txt
cdsapitaka.egg-info/zip-safe
tests/requirements.txt
tests/test_api.py